{
 "Beatrix": {
  "race": "Human",
  "gender": "female"
 },
 "Cagliostro": {
  "race": "Human",
  "gender": "female"
 },
 "Charlotta": {
  "race": "Harvin",
  "gender": "female"
 },
 "Djeeta": {
  "race": "Human",
  "gender": "female"
 },
 "Eugen": {
  "race": "Human",
  "gender": "male"
 },
 "Eustace": {
  "race": "Erune",
  "gender": "male"
 },
 "Fediel": {
  "race": "Primal beast",
  "gender": "female"
 },
 "Ferry": {
  "race": "Draph",
  "gender": "female"
 },
 "Fraux": {
  "race": "Harvin",
  "gender": "female"
 },
 "Gallanza": {
  "race": "Draph",
  "gender": "male"
 },
 "Ghandagoza": {
  "race": "Draph",
  "gender": "male"
 },
 "Gran": {
  "race": "Human",
  "gender": "male"
 },
 "Id": {
  "race": "Draph",
  "gender": "male"
 },
 "Io": {
  "race": "Human",
  "gender": "female"
 },
 "Katalina": {
  "race": "Human",
  "gender": "female"
 },
 "Lancelot": {
  "race": "Human",
  "gender": "male"
 },
 "Maglielle": {
  "race": "Harvin",
  "gender": "female"
 },
 "Narmaya": {
  "race": "Draph",
  "gender": "female"
 },
 "Percival": {
  "race": "Human",
  "gender": "male"
 },
 "Rackam": {
  "race": "Human",
  "gender": "male"
 },
 "Rosetta": {
  "race": "Primal beast",
  "gender": "female"
 },
 "Sandalphon": {
  "race": "Primal beast",
  "gender": "male"
 },
 "Seofon": {
  "race": "Human",
  "gender": "male"
 },
 "Siegfried": {
  "race": "Human",
  "gender": "male"
 },
 "Tweyen": {
  "race": "Erune",
  "gender": "female"
 },
 "Vane": {
  "race": "Human",
  "gender": "male"
 },
 "Vaseraga": {
  "race": "Draph",
  "gender": "male"
 },
 "Yodarha": {
  "race": "Harvin",
  "gender": "male"
 },
 "Zeta": {
  "race": "Erune",
  "gender": "female"
 }
}